[
{"is_superhost": true, "host_id": "46798877", "price": 323.0, "url": "https://www.airbnb.com/rooms/26687950", "bathrooms": 4.0, "bedrooms": 4, "is_business_travel_ready": false, "is_fully_refundable": false, "is_new_listing": false, "lat": 21.13155, "lng": -86.75735, "localized_city": "Canc\u00fan", "localized_neighborhood": null, "listing_name": "Casa Quetzal Cancun \nBella Residencia a la laguna", "person_capacity": 10, "picture_count": 33, "reviews_count": 22, "room_type_category": "entire_home", "star_rating": 4.5, "avg_rating": 4.64, "can_instant_book": false, "monthly_price_factor": 0.9, "weekly_price_factor": 0.95, "currency": "CAD", "amt_w_service": 323.0, "rate_type": "nightly", "num_beds": 7, "host_reviews": 226, "accuracy": 10, "checkin": 10, "cleanliness": 9, "communication": 10, "value": 9, "location": 10, "guest_satisfication": 93, "response_rate": 100, "response_time": "within an hour"},
{"is_superhost": false, "host_id": "2671581", "price": 329.0, "url": "https://www.airbnb.com/rooms/13574373", "bathrooms": 3.0, "bedrooms": 2, "is_business_travel_ready": false, "is_fully_refundable": false, "is_new_listing": false, "lat": 21.10251, "lng": -86.7659, "localized_city": "Canc\u00fan", "localized_neighborhood": null, "listing_name": "AAA Ocean Front Large private suite in resort", "person_capacity": 8, "picture_count": 23, "reviews_count": 5, "room_type_category": "entire_home", "star_rating": 5.0, "avg_rating": 4.75, "can_instant_book": true, "monthly_price_factor": 0.85, "weekly_price_factor": 1.0, "currency": "CAD", "amt_w_service": 329.0, "rate_type": "nightly", "num_beds": 5, "host_reviews": 6, "accuracy": 9, "checkin": 10, "cleanliness": 10, "communication": 10, "value": 9, "location": 10, "guest_satisfication": 95, "response_rate": 100, "response_time": "within a few hours"},
{"is_superhost": false, "host_id": "62113174", "price": 329.0, "url": "https://www.airbnb.com/rooms/14573840", "bathrooms": 3.0, "bedrooms": 3, "is_business_travel_ready": false, "is_fully_refundable": false, "is_new_listing": false, "lat": 21.03115, "lng": -86.81076, "localized_city": "Canc\u00fan", "localized_neighborhood": null, "listing_name": "APARTMENT IN CANCUN2, AMAZING OCEAN VIEW.", "person_capacity": 8, "picture_count": 34, "reviews_count": 7, "room_type_category": "entire_home", "star_rating": 5.0, "avg_rating": 5.0, "can_instant_book": true, "monthly_price_factor": 1.0, "weekly_price_factor": 0.9, "currency": "CAD", "amt_w_service": 329.0, "rate_type": "nightly", "num_beds": 5, "host_reviews": 317, "accuracy": 10, "checkin": 10, "cleanliness": 10, "communication": 10, "value": 10, "location": 9, "guest_satisfication": 100, "response_rate": 100, "response_time": "within an hour"},
{"is_superhost": false, "host_id": "49631487", "price": 329.0, "url": "https://www.airbnb.com/rooms/9823333", "bathrooms": 2.0, "bedrooms": 2, "is_business_travel_ready": false, "is_fully_refundable": false, "is_new_listing": false, "lat": 21.13734, "lng": -86.75266, "localized_city": "Canc\u00fan", "localized_neighborhood": null, "listing_name": "Amazing Beachfront Condo in Cancun Hotel Zone", "person_capacity": 8, "picture_count": 40, "reviews_count": 11, "room_type_category": "entire_home", "star_rating": 4.5, "avg_rating": 4.7, "can_instant_book": true, "monthly_price_factor": 0.7, "weekly_price_factor": 1.0, "currency": "CAD", "amt_w_service": 329.0, "rate_type": "nightly", "num_beds": 3, "host_reviews": 13, "accuracy": 9, "checkin": 10, "cleanliness": 10, "communication": 10, "value": 9, "location": 10, "guest_satisfication": 94, "response_rate": 100, "response_time": "within an hour"},
{"is_superhost": false, "host_id": "27622456", "price": 329.0, "url": "https://www.airbnb.com/rooms/9630756", "bathrooms": 2.5, "bedrooms": 2, "is_business_travel_ready": false, "is_fully_refundable": false, "is_new_listing": false, "lat": 21.12168, "lng": -86.7678, "localized_city": "Canc\u00fan", "localized_neighborhood": null, "listing_name": "Lagoon front PH, Close to the beach", "person_capacity": 6, "picture_count": 30, "reviews_count": 9, "room_type_category": "entire_home", "star_rating": 4.0, "avg_rating": 4.22, "can_instant_book": true, "monthly_price_factor": 1.0, "weekly_price_factor": 1.0, "currency": "CAD", "amt_w_service": 329.0, "rate_type": "nightly", "num_beds": 3, "host_reviews": 633, "accuracy": 9, "checkin": 9, "cleanliness": 9, "communication": 8, "value": 8, "location": 8, "guest_satisfication": 84, "response_rate": 100, "response_time": "within an hour"},
{"is_superhost": false, "host_id": "481799", "price": 327.0, "url": "https://www.airbnb.com/rooms/530250", "bathrooms": 2.5, "bedrooms": 2, "is_business_travel_ready": false, "is_fully_refundable": false, "is_new_listing": false, "lat": 21.209879, "lng": -86.716637, "localized_city": "Isla Mujeres", "localized_neighborhood": null, "listing_name": "The World Famous Seashell House ~ Casa Caracol", "person_capacity": 4, "picture_count": 55, "reviews_count": 227, "room_type_category": "entire_home", "star_rating": 5.0, "avg_rating": 4.78, "can_instant_book": true, "monthly_price_factor": 1.0, "weekly_price_factor": 1.0, "currency": "CAD", "amt_w_service": 327.0, "rate_type": "nightly", "num_beds": 2, "host_reviews": 2551, "accuracy": 10, "checkin": 10, "cleanliness": 10, "communication": 10, "value": 9, "location": 10, "guest_satisfication": 96, "response_rate": 97, "response_time": "within an hour"},
{"is_superhost": true, "host_id": "90672488", "price": 329.0, "url": "https://www.airbnb.com/rooms/23161613", "bathrooms": 3.5, "bedrooms": 3, "is_business_travel_ready": false, "is_fully_refundable": false, "is_new_listing": false, "lat": 21.11635, "lng": -86.75839, "localized_city": "Canc\u00fan", "localized_neighborhood": null, "listing_name": "BRIDEC- OCEAN VIEW APARTMENT DEPTO 1-C", "person_capacity": 8, "picture_count": 27, "reviews_count": 17, "room_type_category": "entire_home", "star_rating": 5.0, "avg_rating": 4.88, "can_instant_book": false, "monthly_price_factor": 1.0, "weekly_price_factor": 1.0, "currency": "CAD", "amt_w_service": 329.0, "rate_type": "nightly", "num_beds": 6, "host_reviews": 71, "accuracy": 10, "checkin": 10, "cleanliness": 9, "communication": 10, "value": 10, "location": 10, "guest_satisfication": 98, "response_rate": 100, "response_time": "within an hour"},
{"is_superhost": false, "host_id": "2417317", "price": 326.0, "url": "https://www.airbnb.com/rooms/31849300", "bathrooms": 3.0, "bedrooms": 4, "is_business_travel_ready": false, "is_fully_refundable": false, "is_new_listing": false, "lat": 21.10217, "lng": -86.76412, "localized_city": "Canc\u00fan", "localized_neighborhood": null, "listing_name": "Ocean View 4 bedroom Villa #14", "person_capacity": 8, "picture_count": 26, "reviews_count": 6, "room_type_category": "entire_home", "star_rating": 4.5, "avg_rating": 4.67, "can_instant_book": true, "monthly_price_factor": 1.0, "weekly_price_factor": 1.0, "currency": "CAD", "amt_w_service": 326.0, "rate_type": "nightly", "num_beds": 5, "host_reviews": 16, "accuracy": 10, "checkin": 9, "cleanliness": 9, "communication": 10, "value": 9, "location": 9, "guest_satisfication": 93, "response_rate": 100, "response_time": "within an hour"},
{"is_superhost": false, "host_id": "76588648", "price": 329.0, "url": "https://www.airbnb.com/rooms/24076333", "bathrooms": 3.0, "bedrooms": 3, "is_business_travel_ready": false, "is_fully_refundable": false, "is_new_listing": false, "lat": 21.182459, "lng": -86.808487, "localized_city": "Canc\u00fan", "localized_neighborhood": null, "listing_name": "Amara Beach Front Panoramic", "person_capacity": 9, "picture_count": 27, "reviews_count": 20, "room_type_category": "entire_home", "star_rating": 5.0, "avg_rating": 5.0, "can_instant_book": true, "monthly_price_factor": 1.0, "weekly_price_factor": 0.9, "currency": "CAD", "amt_w_service": 329.0, "rate_type": "nightly", "num_beds": 5, "host_reviews": 109, "accuracy": 10, "checkin": 10, "cleanliness": 10, "communication": 10, "value": 10, "location": 9, "guest_satisfication": 100, "response_rate": 100, "response_time": "within a day"},
{"is_superhost": false, "host_id": "94261034", "price": 329.0, "url": "https://www.airbnb.com/rooms/16826035", "bathrooms": 3.0, "bedrooms": 2, "is_business_travel_ready": false, "is_fully_refundable": false, "is_new_listing": false, "lat": 21.13168, "lng": -86.74939, "localized_city": "Canc\u00fan", "localized_neighborhood": null, "listing_name": "Penthouse 10", "person_capacity": 6, "picture_count": 51, "reviews_count": 9, "room_type_category": "entire_home", "star_rating": 5.0, "avg_rating": 4.89, "can_instant_book": true, "monthly_price_factor": 0.8, "weekly_price_factor": 1.0, "currency": "CAD", "amt_w_service": 329.0, "rate_type": "nightly", "num_beds": 4, "host_reviews": 145, "accuracy": 10, "checkin": 10, "cleanliness": 10, "communication": 10, "value": 10, "location": 10, "guest_satisfication": 98, "response_rate": 100, "response_time": "within an hour"},
{"is_superhost": true, "host_id": "14289206", "price": 329.0, "url": "https://www.airbnb.com/rooms/11847103", "bathrooms": 3.0, "bedrooms": 3, "is_business_travel_ready": false, "is_fully_refundable": false, "is_new_listing": false, "lat": 21.03835, "lng": -86.78532, "localized_city": "Canc\u00fan", "localized_neighborhood": null, "listing_name": "APARTMENT CANCUN, OCEAN VIEW2. by OctopusTravel", "person_capacity": 8, "picture_count": 38, "reviews_count": 13, "room_type_category": "entire_home", "star_rating": 5.0, "avg_rating": 4.77, "can_instant_book": true, "monthly_price_factor": 1.0, "weekly_price_factor": 0.9, "currency": "CAD", "amt_w_service": 329.0, "rate_type": "nightly", "num_beds": 5, "host_reviews": 421, "accuracy": 10, "checkin": 10, "cleanliness": 10, "communication": 10, "value": 10, "location": 9, "guest_satisfication": 95, "response_rate": 100, "response_time": "within an hour"},
{"is_superhost": false, "host_id": "35476937", "price": 329.0, "url": "https://www.airbnb.com/rooms/9826099", "bathrooms": 4.0, "bedrooms": 4, "is_business_travel_ready": false, "is_fully_refundable": false, "is_new_listing": false, "lat": 21.090376, "lng": -86.770897, "localized_city": "Canc\u00fan", "localized_neighborhood": null, "listing_name": "Luxury Residence!! - Hotel Zone - Cancun", "person_capacity": 10, "picture_count": 38, "reviews_count": 19, "room_type_category": "entire_home", "star_rating": 4.5, "avg_rating": 4.44, "can_instant_book": true, "monthly_price_factor": 1.0, "weekly_price_factor": 0.97, "currency": "CAD", "amt_w_service": 329.0, "rate_type": "nightly", "num_beds": 7, "host_reviews": 184, "accuracy": 9, "checkin": 10, "cleanliness": 9, "communication": 9, "value": 9, "location": 10, "guest_satisfication": 89, "response_rate": 100, "response_time": "within an hour"},
{"is_superhost": true, "host_id": "105873411", "price": 329.0, "url": "https://www.airbnb.com/rooms/22789281", "bathrooms": 1.0, "bedrooms": 1, "is_business_travel_ready": false, "is_fully_refundable": false, "is_new_listing": false, "lat": 21.05384, "lng": -86.78205, "localized_city": "Canc\u00fan", "localized_neighborhood": null, "listing_name": "Master Penthouse", "person_capacity": 2, "picture_count": 23, "reviews_count": 3, "room_type_category": "entire_home", "star_rating": 5.0, "avg_rating": 5.0, "can_instant_book": false, "monthly_price_factor": 1.0, "weekly_price_factor": 1.0, "currency": "CAD", "amt_w_service": 329.0, "rate_type": "nightly", "num_beds": 1, "host_reviews": 65, "accuracy": 10, "checkin": 9, "cleanliness": 10, "communication": 10, "value": 9, "location": 10, "guest_satisfication": 100, "response_rate": 98, "response_time": "within an hour"},
{"is_superhost": true, "host_id": "146467982", "price": 329.0, "url": "https://www.airbnb.com/rooms/28604984", "bathrooms": 1.5, "bedrooms": 1, "is_business_travel_ready": false, "is_fully_refundable": false, "is_new_listing": false, "lat": 21.14576, "lng": -86.78973, "localized_city": "Canc\u00fan", "localized_neighborhood": null, "listing_name": "Beachfront Condo with Terrace Walkout", "person_capacity": 2, "picture_count": 52, "reviews_count": 10, "room_type_category": "entire_home", "star_rating": 5.0, "avg_rating": 5.0, "can_instant_book": true, "monthly_price_factor": 0.9, "weekly_price_factor": 0.96, "currency": "CAD", "amt_w_service": 329.0, "rate_type": "nightly", "num_beds": 1, "host_reviews": 18, "accuracy": 10, "checkin": 10, "cleanliness": 10, "communication": 10, "value": 10, "location": 10, "guest_satisfication": 100, "response_rate": 100, "response_time": "within an hour"},
{"is_superhost": true, "host_id": "25509760", "price": 327.0, "url": "https://www.airbnb.com/rooms/13748142", "bathrooms": 2.5, "bedrooms": 2, "is_business_travel_ready": false, "is_fully_refundable": false, "is_new_listing": false, "lat": 21.257673, "lng": -86.749344, "localized_city": "Isla Mujeres", "localized_neighborhood": null, "listing_name": "New Downtown penthouse, with beautiful ocean view!", "person_capacity": 5, "picture_count": 24, "reviews_count": 59, "room_type_category": "entire_home", "star_rating": 5.0, "avg_rating": 4.91, "can_instant_book": true, "monthly_price_factor": 0.8, "weekly_price_factor": 0.9, "currency": "CAD", "amt_w_service": 327.0, "rate_type": "nightly", "num_beds": 3, "host_reviews": 92, "accuracy": 10, "checkin": 10, "cleanliness": 10, "communication": 10, "value": 10, "location": 10, "guest_satisfication": 98, "response_rate": 100, "response_time": "within an hour"},
{"is_superhost": false, "host_id": "21090229", "price": 329.0, "url": "https://www.airbnb.com/rooms/4131595", "bathrooms": 4.0, "bedrooms": 3, "is_business_travel_ready": false, "is_fully_refundable": false, "is_new_listing": false, "lat": 21.10426, "lng": -86.7579, "localized_city": "Canc\u00fan", "localized_neighborhood": null, "listing_name": "3 BR Ocean View Apartment", "person_capacity": 10, "picture_count": 17, "reviews_count": 5, "room_type_category": "entire_home", "star_rating": 5.0, "avg_rating": 4.8, "can_instant_book": false, "monthly_price_factor": 1.0, "weekly_price_factor": 1.0, "currency": "CAD", "amt_w_service": 329.0, "rate_type": "nightly", "num_beds": 6, "host_reviews": 83, "accuracy": 9, "checkin": 10, "cleanliness": 10, "communication": 10, "value": 9, "location": 10, "guest_satisfication": 96, "response_rate": 70, "response_time": "within a day"},
{"is_superhost": false, "host_id": "44008309", "price": 329.0, "url": "https://www.airbnb.com/rooms/24580189", "bathrooms": 2.0, "bedrooms": 2, "is_business_travel_ready": false, "is_fully_refundable": false, "is_new_listing": false, "lat": 21.19336, "lng": -86.80642, "localized_city": "Canc\u00fan", "localized_neighborhood": null, "listing_name": "El Cielo - Beachfront/Infinity pool/Wifi 60Mb", "person_capacity": 4, "picture_count": 41, "reviews_count": 1, "room_type_category": "entire_home", "star_rating": null, "avg_rating": 5.0, "can_instant_book": false, "monthly_price_factor": 1.0, "weekly_price_factor": 1.0, "currency": "CAD", "amt_w_service": 329.0, "rate_type": "nightly", "num_beds": 2, "host_reviews": 3, "accuracy": 10, "checkin": 10, "cleanliness": 8, "communication": 10, "value": 10, "location": 10, "guest_satisfication": 100, "response_rate": 0, "response_time": ""},
{"is_superhost": false, "host_id": "120561911", "price": 326.0, "url": "https://www.airbnb.com/rooms/26638590", "bathrooms": 3.5, "bedrooms": 3, "is_business_travel_ready": false, "is_fully_refundable": false, "is_new_listing": false, "lat": 21.03268, "lng": -86.80608, "localized_city": "Canc\u00fan", "localized_neighborhood": null, "listing_name": "CANCUN, APARTMENT WITH OCEAN VIEW, PRIVATE BEACH.", "person_capacity": 8, "picture_count": 19, "reviews_count": 5, "room_type_category": "entire_home", "star_rating": 5.0, "avg_rating": 5.0, "can_instant_book": true, "monthly_price_factor": 1.0, "weekly_price_factor": 0.9, "currency": "CAD", "amt_w_service": 326.0, "rate_type": "nightly", "num_beds": 5, "host_reviews": 85, "accuracy": 10, "checkin": 9, "cleanliness": 10, "communication": 9, "value": 10, "location": 10, "guest_satisfication": 100, "response_rate": 100, "response_time": "within an hour"},
{"is_superhost": false, "host_id": "214899222", "price": 329.0, "url": "https://www.airbnb.com/rooms/33906261", "bathrooms": 3.0, "bedrooms": 3, "is_business_travel_ready": false, "is_fully_refundable": false, "is_new_listing": false, "lat": 21.13471, "lng": -86.74519, "localized_city": "Canc\u00fan", "localized_neighborhood": null, "listing_name": "Krystal CANCUN Quintana Roo", "person_capacity": 6, "picture_count": 22, "reviews_count": 0, "room_type_category": "private_room", "star_rating": null, "avg_rating": 0.0, "can_instant_book": true, "monthly_price_factor": 0.9, "weekly_price_factor": 0.95, "currency": "CAD", "amt_w_service": 329.0, "rate_type": "nightly", "num_beds": 3, "host_reviews": 1, "accuracy": 0, "checkin": 0, "cleanliness": 0, "communication": 0, "value": 0, "location": 0, "guest_satisfication": 0, "response_rate": 0, "response_time": ""},
{"is_superhost": false, "host_id": "10352971", "price": 321.0, "url": "https://www.airbnb.com/rooms/20297694", "bathrooms": 3.0, "bedrooms": 3, "is_business_travel_ready": false, "is_fully_refundable": false, "is_new_listing": false, "lat": 21.031601, "lng": -86.807495, "localized_city": "Canc\u00fan", "localized_neighborhood": null, "listing_name": "Beach Front luxury apartment Cancun hotel zone", "person_capacity": 6, "picture_count": 49, "reviews_count": 0, "room_type_category": "entire_home", "star_rating": null, "avg_rating": 0.0, "can_instant_book": true, "monthly_price_factor": 0.8, "weekly_price_factor": 1.0, "currency": "CAD", "amt_w_service": 321.0, "rate_type": "nightly", "num_beds": 3, "host_reviews": 1, "accuracy": 0, "checkin": 0, "cleanliness": 0, "communication": 0, "value": 0, "location": 0, "guest_satisfication": 0, "response_rate": 100, "response_time": "within a day"},
{"is_superhost": true, "host_id": "34694262", "price": 329.0, "url": "https://www.airbnb.com/rooms/27954713", "bathrooms": 3.5, "bedrooms": 3, "is_business_travel_ready": false, "is_fully_refundable": false, "is_new_listing": false, "lat": 21.23522, "lng": -86.73211, "localized_city": "Isla Mujeres", "localized_neighborhood": null, "listing_name": "MAYAKAAN HOUSES, FANTASTIC BEACH VIEW w/ROOFTOP", "person_capacity": 8, "picture_count": 41, "reviews_count": 21, "room_type_category": "entire_home", "star_rating": 5.0, "avg_rating": 4.95, "can_instant_book": true, "monthly_price_factor": 0.8, "weekly_price_factor": 0.9, "currency": "CAD", "amt_w_service": 329.0, "rate_type": "nightly", "num_beds": 5, "host_reviews": 67, "accuracy": 10, "checkin": 10, "cleanliness": 10, "communication": 10, "value": 10, "location": 10, "guest_satisfication": 99, "response_rate": 100, "response_time": "within an hour"},
{"is_superhost": true, "host_id": "75625340", "price": 329.0, "url": "https://www.airbnb.com/rooms/20033715", "bathrooms": 2.5, "bedrooms": 3, "is_business_travel_ready": false, "is_fully_refundable": false, "is_new_listing": false, "lat": 21.1014, "lng": -86.7651, "localized_city": "Canc\u00fan", "localized_neighborhood": null, "listing_name": "Beautiful apartment with wonderful view of the sea", "person_capacity": 6, "picture_count": 35, "reviews_count": 23, "room_type_category": "entire_home", "star_rating": 5.0, "avg_rating": 4.87, "can_instant_book": true, "monthly_price_factor": 0.8, "weekly_price_factor": 0.9, "currency": "CAD", "amt_w_service": 329.0, "rate_type": "nightly", "num_beds": 4, "host_reviews": 23, "accuracy": 10, "checkin": 10, "cleanliness": 10, "communication": 10, "value": 10, "location": 10, "guest_satisfication": 97, "response_rate": 100, "response_time": "within an hour"},
{"is_superhost": false, "host_id": "143382643", "price": 329.0, "url": "https://www.airbnb.com/rooms/20152697", "bathrooms": 4.5, "bedrooms": 3, "is_business_travel_ready": false, "is_fully_refundable": false, "is_new_listing": false, "lat": 21.098585, "lng": -86.844994, "localized_city": "Canc\u00fan", "localized_neighborhood": null, "listing_name": "Luxury House in Canc\u00fan. Private Pool.", "person_capacity": 12, "picture_count": 11, "reviews_count": 8, "room_type_category": "entire_home", "star_rating": 5.0, "avg_rating": 4.88, "can_instant_book": false, "monthly_price_factor": 0.5, "weekly_price_factor": 1.0, "currency": "CAD", "amt_w_service": 329.0, "rate_type": "nightly", "num_beds": 5, "host_reviews": 8, "accuracy": 10, "checkin": 10, "cleanliness": 10, "communication": 10, "value": 10, "location": 10, "guest_satisfication": 98, "response_rate": 100, "response_time": "within a day"},
{"is_superhost": false, "host_id": "214713410", "price": 329.0, "url": "https://www.airbnb.com/rooms/30082473", "bathrooms": 1.0, "bedrooms": 0, "is_business_travel_ready": false, "is_fully_refundable": false, "is_new_listing": false, "lat": 21.09086, "lng": -86.77243, "localized_city": "Canc\u00fan", "localized_neighborhood": null, "listing_name": "Beautiful Resort in Cancun", "person_capacity": 4, "picture_count": 5, "reviews_count": 1, "room_type_category": "private_room", "star_rating": null, "avg_rating": 0.0, "can_instant_book": false, "monthly_price_factor": 1.0, "weekly_price_factor": 1.0, "currency": "CAD", "amt_w_service": 329.0, "rate_type": "nightly", "num_beds": 2, "host_reviews": 24, "accuracy": 0, "checkin": 0, "cleanliness": 0, "communication": 0, "value": 0, "location": 0, "guest_satisfication": 0, "response_rate": 88, "response_time": "within an hour"},
{"is_superhost": false, "host_id": "109741422", "price": 322.0, "url": "https://www.airbnb.com/rooms/24056681", "bathrooms": 2.0, "bedrooms": 2, "is_business_travel_ready": false, "is_fully_refundable": false, "is_new_listing": false, "lat": 21.11075, "lng": -86.76314, "localized_city": "Canc\u00fan", "localized_neighborhood": null, "listing_name": "Westin Lagunamar Ocean Resort Villas (2019)", "person_capacity": 8, "picture_count": 21, "reviews_count": 0, "room_type_category": "entire_home", "star_rating": null, "avg_rating": 0.0, "can_instant_book": false, "monthly_price_factor": 1.0, "weekly_price_factor": 1.0, "currency": "CAD", "amt_w_service": 322.0, "rate_type": "nightly", "num_beds": 4, "host_reviews": 4, "accuracy": 0, "checkin": 0, "cleanliness": 0, "communication": 0, "value": 0, "location": 0, "guest_satisfication": 0, "response_rate": 100, "response_time": "within an hour"},
{"is_superhost": false, "host_id": "71173970", "price": 329.0, "url": "https://www.airbnb.com/rooms/14189206", "bathrooms": 2.0, "bedrooms": 3, "is_business_travel_ready": false, "is_fully_refundable": false, "is_new_listing": false, "lat": 21.14722, "lng": -86.7926, "localized_city": "Canc\u00fan", "localized_neighborhood": null, "listing_name": "KATE, impresionante Yate muy c\u00f3modo", "person_capacity": 6, "picture_count": 40, "reviews_count": 0, "room_type_category": "entire_home", "star_rating": null, "avg_rating": 0.0, "can_instant_book": false, "monthly_price_factor": 0.8, "weekly_price_factor": 0.9, "currency": "CAD", "amt_w_service": 329.0, "rate_type": "nightly", "num_beds": 4, "host_reviews": 30, "accuracy": 0, "checkin": 0, "cleanliness": 0, "communication": 0, "value": 0, "location": 0, "guest_satisfication": 0, "response_rate": 90, "response_time": "within a few hours"},
{"is_superhost": false, "host_id": "135113785", "price": 329.0, "url": "https://www.airbnb.com/rooms/34601726", "bathrooms": 1.0, "bedrooms": 1, "is_business_travel_ready": false, "is_fully_refundable": false, "is_new_listing": true, "lat": 21.13326, "lng": -86.74396, "localized_city": "Canc\u00fan", "localized_neighborhood": null, "listing_name": "Rec\u00e1mara con vista al mar, con la mejor ubicaci\u00f3n!", "person_capacity": 4, "picture_count": 4, "reviews_count": 0, "room_type_category": "private_room", "star_rating": null, "avg_rating": 0.0, "can_instant_book": true, "monthly_price_factor": 1.0, "weekly_price_factor": 1.0, "currency": "CAD", "amt_w_service": 329.0, "rate_type": "nightly", "num_beds": 2, "host_reviews": 0, "accuracy": 0, "checkin": 0, "cleanliness": 0, "communication": 0, "value": 0, "location": 0, "guest_satisfication": 0, "response_rate": 0, "response_time": ""},
{"is_superhost": false, "host_id": "37225043", "price": 327.0, "url": "https://www.airbnb.com/rooms/7104995", "bathrooms": 2.0, "bedrooms": 3, "is_business_travel_ready": false, "is_fully_refundable": false, "is_new_listing": false, "lat": 20.89857, "lng": -86.85475, "localized_city": "Puerto Morelos", "localized_neighborhood": null, "listing_name": "On the beach luxury apartment The Beach Residences", "person_capacity": 7, "picture_count": 42, "reviews_count": 41, "room_type_category": "entire_home", "star_rating": 5.0, "avg_rating": 4.83, "can_instant_book": true, "monthly_price_factor": 0.75, "weekly_price_factor": 0.9, "currency": "CAD", "amt_w_service": 327.0, "rate_type": "nightly", "num_beds": 5, "host_reviews": 41, "accuracy": 10, "checkin": 10, "cleanliness": 10, "communication": 10, "value": 10, "location": 9, "guest_satisfication": 97, "response_rate": 100, "response_time": "within an hour"},
{"is_superhost": true, "host_id": "70694723", "price": 322.0, "url": "https://www.airbnb.com/rooms/13078037", "bathrooms": 4.0, "bedrooms": 5, "is_business_travel_ready": false, "is_fully_refundable": false, "is_new_listing": false, "lat": 21.235338, "lng": -86.731201, "localized_city": "Isla Mujeres", "localized_neighborhood": null, "listing_name": "Luxury Ocean Front 5 Bdrm+Pool+Jacuzzi+ 360 VIEWS!", "person_capacity": 10, "picture_count": 79, "reviews_count": 1, "room_type_category": "entire_home", "star_rating": null, "avg_rating": 5.0, "can_instant_book": true, "monthly_price_factor": 1.0, "weekly_price_factor": 1.0, "currency": "CAD", "amt_w_service": 322.0, "rate_type": "nightly", "num_beds": 7, "host_reviews": 220, "accuracy": 10, "checkin": 10, "cleanliness": 10, "communication": 10, "value": 10, "location": 10, "guest_satisfication": 100, "response_rate": 100, "response_time": "within an hour"},
{"is_superhost": false, "host_id": "10352971", "price": 327.0, "url": "https://www.airbnb.com/rooms/33787692", "bathrooms": 3.0, "bedrooms": 3, "is_business_travel_ready": false, "is_fully_refundable": false, "is_new_listing": false, "lat": 21.03065, "lng": -86.80684, "localized_city": "Canc\u00fan", "localized_neighborhood": null, "listing_name": "Ocean View Luxury Apartment in Cancun Hotel Zone", "person_capacity": 6, "picture_count": 58, "reviews_count": 0, "room_type_category": "entire_home", "star_rating": null, "avg_rating": 0.0, "can_instant_book": true, "monthly_price_factor": 0.79, "weekly_price_factor": 1.0, "currency": "CAD", "amt_w_service": 327.0, "rate_type": "nightly", "num_beds": 3, "host_reviews": 1, "accuracy": 0, "checkin": 0, "cleanliness": 0, "communication": 0, "value": 0, "location": 0, "guest_satisfication": 0, "response_rate": 100, "response_time": "within a day"},
{"is_superhost": false, "host_id": "133647282", "price": 329.0, "url": "https://www.airbnb.com/rooms/29056331", "bathrooms": 2.0, "bedrooms": 3, "is_business_travel_ready": false, "is_fully_refundable": false, "is_new_listing": false, "lat": 20.85531, "lng": -86.87153, "localized_city": "Puerto Morelos", "localized_neighborhood": null, "listing_name": "Welcome to Paradise in Puerto Morelos", "person_capacity": 6, "picture_count": 29, "reviews_count": 0, "room_type_category": "entire_home", "star_rating": null, "avg_rating": 0.0, "can_instant_book": true, "monthly_price_factor": 1.0, "weekly_price_factor": 1.0, "currency": "CAD", "amt_w_service": 329.0, "rate_type": "nightly", "num_beds": 3, "host_reviews": 0, "accuracy": 0, "checkin": 0, "cleanliness": 0, "communication": 0, "value": 0, "location": 0, "guest_satisfication": 0, "response_rate": 0, "response_time": ""},
{"is_superhost": true, "host_id": "90717918", "price": 329.0, "url": "https://www.airbnb.com/rooms/35743637", "bathrooms": 2.0, "bedrooms": 2, "is_business_travel_ready": false, "is_fully_refundable": false, "is_new_listing": true, "lat": 21.23549, "lng": -86.73021, "localized_city": "Isla Mujeres", "localized_neighborhood": null, "listing_name": "Casa Mango Penthouse", "person_capacity": 4, "picture_count": 51, "reviews_count": 0, "room_type_category": "entire_home", "star_rating": null, "avg_rating": 0.0, "can_instant_book": false, "monthly_price_factor": 0.75, "weekly_price_factor": 0.9, "currency": "CAD", "amt_w_service": 329.0, "rate_type": "nightly", "num_beds": 2, "host_reviews": 62, "accuracy": 0, "checkin": 0, "cleanliness": 0, "communication": 0, "value": 0, "location": 0, "guest_satisfication": 0, "response_rate": 100, "response_time": "within an hour"},
{"is_superhost": false, "host_id": "134617463", "price": 329.0, "url": "https://www.airbnb.com/rooms/19228669", "bathrooms": 1.0, "bedrooms": 1, "is_business_travel_ready": false, "is_fully_refundable": false, "is_new_listing": false, "lat": 21.0508, "lng": -86.78357, "localized_city": "Canc\u00fan", "localized_neighborhood": null, "listing_name": "Presidential suit Cancun Hotel Zone", "person_capacity": 4, "picture_count": 18, "reviews_count": 0, "room_type_category": "entire_home", "star_rating": null, "avg_rating": 0.0, "can_instant_book": false, "monthly_price_factor": 1.0, "weekly_price_factor": 1.0, "currency": "CAD", "amt_w_service": 329.0, "rate_type": "nightly", "num_beds": 3, "host_reviews": 0, "accuracy": 0, "checkin": 0, "cleanliness": 0, "communication": 0, "value": 0, "location": 0, "guest_satisfication": 0, "response_rate": 0, "response_time": ""},
{"is_superhost": false, "host_id": "85114018", "price": 329.0, "url": "https://www.airbnb.com/rooms/35410211", "bathrooms": 2.0, "bedrooms": 2, "is_business_travel_ready": false, "is_fully_refundable": false, "is_new_listing": true, "lat": 21.24124, "lng": -86.80391, "localized_city": "Canc\u00fan", "localized_neighborhood": null, "listing_name": "Mexican luxury 5* resort 2bed apt in paradise!", "person_capacity": 4, "picture_count": 25, "reviews_count": 0, "room_type_category": "entire_home", "star_rating": null, "avg_rating": 0.0, "can_instant_book": false, "monthly_price_factor": 0.85, "weekly_price_factor": 1.0, "currency": "CAD", "amt_w_service": 329.0, "rate_type": "nightly", "num_beds": 3, "host_reviews": 3, "accuracy": 0, "checkin": 0, "cleanliness": 0, "communication": 0, "value": 0, "location": 0, "guest_satisfication": 0, "response_rate": 0, "response_time": ""},
{"is_superhost": false, "host_id": "146152791", "price": 329.0, "url": "https://www.airbnb.com/rooms/20469618", "bathrooms": 2.0, "bedrooms": 2, "is_business_travel_ready": false, "is_fully_refundable": false, "is_new_listing": false, "lat": 21.23241, "lng": -86.72759, "localized_city": "Isla Mujeres", "localized_neighborhood": null, "listing_name": "Ocean Front Isla Mujeres - Beautiful and Sleeps 4", "person_capacity": 4, "picture_count": 8, "reviews_count": 5, "room_type_category": "entire_home", "star_rating": 5.0, "avg_rating": 5.0, "can_instant_book": false, "monthly_price_factor": 1.0, "weekly_price_factor": 1.0, "currency": "CAD", "amt_w_service": 329.0, "rate_type": "nightly", "num_beds": 2, "host_reviews": 6, "accuracy": 10, "checkin": 10, "cleanliness": 10, "communication": 10, "value": 8, "location": 9, "guest_satisfication": 100, "response_rate": 100, "response_time": "within a day"},
{"is_superhost": true, "host_id": "34694262", "price": 329.0, "url": "https://www.airbnb.com/rooms/33184074", "bathrooms": 3.5, "bedrooms": 3, "is_business_travel_ready": false, "is_fully_refundable": false, "is_new_listing": false, "lat": 21.21895, "lng": -86.72252, "localized_city": "Isla Mujeres", "localized_neighborhood": null, "listing_name": "MAYAKAAN, ISLA MUJERES HOUSES FANTASTIC BEACH VIEW", "person_capacity": 8, "picture_count": 46, "reviews_count": 1, "room_type_category": "entire_home", "star_rating": null, "avg_rating": 5.0, "can_instant_book": true, "monthly_price_factor": 0.8, "weekly_price_factor": 0.9, "currency": "CAD", "amt_w_service": 329.0, "rate_type": "nightly", "num_beds": 5, "host_reviews": 67, "accuracy": 10, "checkin": 10, "cleanliness": 10, "communication": 10, "value": 10, "location": 10, "guest_satisfication": 100, "response_rate": 100, "response_time": "within an hour"},
{"is_superhost": false, "host_id": "55025320", "price": 326.0, "url": "https://www.airbnb.com/rooms/10654785", "bathrooms": 5.0, "bedrooms": 5, "is_business_travel_ready": false, "is_fully_refundable": false, "is_new_listing": false, "lat": 21.11139, "lng": -86.96593, "localized_city": "Canc\u00fan", "localized_neighborhood": null, "listing_name": "Hacienda Familiar El Ramonal Cancun", "person_capacity": 10, "picture_count": 19, "reviews_count": 7, "room_type_category": "entire_home", "star_rating": 4.5, "avg_rating": 4.71, "can_instant_book": true, "monthly_price_factor": 0.65, "weekly_price_factor": 0.9, "currency": "CAD", "amt_w_service": 326.0, "rate_type": "nightly", "num_beds": 1, "host_reviews": 24, "accuracy": 9, "checkin": 10, "cleanliness": 10, "communication": 10, "value": 9, "location": 9, "guest_satisfication": 94, "response_rate": 91, "response_time": "within a few hours"},
{"is_superhost": false, "host_id": "166864109", "price": 329.0, "url": "https://www.airbnb.com/rooms/22655313", "bathrooms": 1.0, "bedrooms": 1, "is_business_travel_ready": false, "is_fully_refundable": false, "is_new_listing": false, "lat": 20.8545, "lng": -86.87178, "localized_city": "Puerto Morelos", "localized_neighborhood": null, "listing_name": "NEW Spectacular apartment Oceanview Puerto Morelos", "person_capacity": 3, "picture_count": 16, "reviews_count": 3, "room_type_category": "entire_home", "star_rating": 5.0, "avg_rating": 5.0, "can_instant_book": false, "monthly_price_factor": 0.9, "weekly_price_factor": 0.93, "currency": "CAD", "amt_w_service": 329.0, "rate_type": "nightly", "num_beds": 1, "host_reviews": 39, "accuracy": 10, "checkin": 10, "cleanliness": 10, "communication": 10, "value": 10, "location": 10, "guest_satisfication": 100, "response_rate": 100, "response_time": "within an hour"},
{"is_superhost": false, "host_id": "88507776", "price": 329.0, "url": "https://www.airbnb.com/rooms/30667999", "bathrooms": 2.0, "bedrooms": 1, "is_business_travel_ready": false, "is_fully_refundable": false, "is_new_listing": false, "lat": 21.23125, "lng": -86.80445, "localized_city": "Canc\u00fan", "localized_neighborhood": null, "listing_name": "1 Bdrm/ 2 Full-Bath, Villa Del Palmar, Cancun", "person_capacity": 4, "picture_count": 30, "reviews_count": 1, "room_type_category": "private_room", "star_rating": null, "avg_rating": 5.0, "can_instant_book": false, "monthly_price_factor": 1.0, "weekly_price_factor": 1.0, "currency": "CAD", "amt_w_service": 329.0, "rate_type": "nightly", "num_beds": 2, "host_reviews": 6, "accuracy": 10, "checkin": 10, "cleanliness": 10, "communication": 10, "value": 10, "location": 10, "guest_satisfication": 100, "response_rate": 100, "response_time": "within an hour"},
{"is_superhost": false, "host_id": "138744766", "price": 327.0, "url": "https://www.airbnb.com/rooms/31222145", "bathrooms": 2.0, "bedrooms": 4, "is_business_travel_ready": false, "is_fully_refundable": false, "is_new_listing": false, "lat": 21.15796, "lng": -86.8409, "localized_city": "Canc\u00fan", "localized_neighborhood": null, "listing_name": "Gorgeous Private 4 Bedrooms 2 Baths & 2 Kitchens", "person_capacity": 12, "picture_count": 13, "reviews_count": 0, "room_type_category": "entire_home", "star_rating": null, "avg_rating": 0.0, "can_instant_book": false, "monthly_price_factor": 1.0, "weekly_price_factor": 1.0, "currency": "CAD", "amt_w_service": 327.0, "rate_type": "nightly", "num_beds": 6, "host_reviews": 2, "accuracy": 0, "checkin": 0, "cleanliness": 0, "communication": 0, "value": 0, "location": 0, "guest_satisfication": 0, "response_rate": 0, "response_time": ""},
{"is_superhost": false, "host_id": "17066390", "price": 329.0, "url": "https://www.airbnb.com/rooms/23505815", "bathrooms": 1.0, "bedrooms": 1, "is_business_travel_ready": false, "is_fully_refundable": false, "is_new_listing": false, "lat": 21.10832, "lng": -86.76219, "localized_city": "Canc\u00fan", "localized_neighborhood": null, "listing_name": "Westin Lagunamar Cancun 1BR 1BA oceanfront Villa", "person_capacity": 4, "picture_count": 11, "reviews_count": 0, "room_type_category": "private_room", "star_rating": null, "avg_rating": 0.0, "can_instant_book": false, "monthly_price_factor": 1.0, "weekly_price_factor": 1.0, "currency": "CAD", "amt_w_service": 329.0, "rate_type": "nightly", "num_beds": 2, "host_reviews": 1, "accuracy": 0, "checkin": 0, "cleanliness": 0, "communication": 0, "value": 0, "location": 0, "guest_satisfication": 0, "response_rate": 100, "response_time": "within a day"},
{"is_superhost": false, "host_id": "171034788", "price": 329.0, "url": "https://www.airbnb.com/rooms/27259428", "bathrooms": 1.0, "bedrooms": 1, "is_business_travel_ready": false, "is_fully_refundable": false, "is_new_listing": false, "lat": 21.11848, "lng": -86.7689, "localized_city": "Canc\u00fan", "localized_neighborhood": null, "listing_name": "Cancun Beachfront Suite with Pool A/C", "person_capacity": 4, "picture_count": 7, "reviews_count": 0, "room_type_category": "private_room", "star_rating": null, "avg_rating": 0.0, "can_instant_book": false, "monthly_price_factor": 1.0, "weekly_price_factor": 1.0, "currency": "CAD", "amt_w_service": 329.0, "rate_type": "nightly", "num_beds": 2, "host_reviews": 0, "accuracy": 0, "checkin": 0, "cleanliness": 0, "communication": 0, "value": 0, "location": 0, "guest_satisfication": 0, "response_rate": 0, "response_time": ""},
{"is_superhost": false, "host_id": "248337590", "price": 329.0, "url": "https://www.airbnb.com/rooms/32995461", "bathrooms": 2.0, "bedrooms": 3, "is_business_travel_ready": false, "is_fully_refundable": false, "is_new_listing": false, "lat": 20.90041, "lng": -86.85261, "localized_city": "Puerto Morelos", "localized_neighborhood": null, "listing_name": "Luxury beach residence", "person_capacity": 8, "picture_count": 23, "reviews_count": 1, "room_type_category": "entire_home", "star_rating": null, "avg_rating": 5.0, "can_instant_book": false, "monthly_price_factor": 1.0, "weekly_price_factor": 0.79, "currency": "CAD", "amt_w_service": 329.0, "rate_type": "nightly", "num_beds": 4, "host_reviews": 1, "accuracy": 10, "checkin": 10, "cleanliness": 10, "communication": 10, "value": 10, "location": 10, "guest_satisfication": 100, "response_rate": 0, "response_time": ""},
{"is_superhost": false, "host_id": "86886362", "price": 329.0, "url": "https://www.airbnb.com/rooms/20679322", "bathrooms": 2.0, "bedrooms": 3, "is_business_travel_ready": false, "is_fully_refundable": false, "is_new_listing": false, "lat": 21.18108, "lng": -86.80667, "localized_city": "Quintana Roo", "localized_neighborhood": null, "listing_name": "Departamento frente al mar con tres rec\u00e1maras", "person_capacity": 6, "picture_count": 16, "reviews_count": 0, "room_type_category": "entire_home", "star_rating": null, "avg_rating": 0.0, "can_instant_book": false, "monthly_price_factor": 0.6, "weekly_price_factor": 0.9, "currency": "CAD", "amt_w_service": 329.0, "rate_type": "nightly", "num_beds": 4, "host_reviews": 1, "accuracy": 0, "checkin": 0, "cleanliness": 0, "communication": 0, "value": 0, "location": 0, "guest_satisfication": 0, "response_rate": 100, "response_time": "within a day"},
{"is_superhost": true, "host_id": "156466665", "price": 329.0, "url": "https://www.airbnb.com/rooms/24381108", "bathrooms": 5.5, "bedrooms": 5, "is_business_travel_ready": false, "is_fully_refundable": false, "is_new_listing": false, "lat": 21.2523, "lng": -86.74489, "localized_city": "Isla Mujeres", "localized_neighborhood": null, "listing_name": "La casa de Lolo Lorena", "person_capacity": 10, "picture_count": 50, "reviews_count": 0, "room_type_category": "entire_home", "star_rating": null, "avg_rating": 0.0, "can_instant_book": false, "monthly_price_factor": 0.55, "weekly_price_factor": 0.9, "currency": "CAD", "amt_w_service": 329.0, "rate_type": "nightly", "num_beds": 1, "host_reviews": 84, "accuracy": 0, "checkin": 0, "cleanliness": 0, "communication": 0, "value": 0, "location": 0, "guest_satisfication": 0, "response_rate": 100, "response_time": "within an hour"},
{"is_superhost": false, "host_id": "172266131", "price": 327.0, "url": "https://www.airbnb.com/rooms/32103526", "bathrooms": 2.0, "bedrooms": 3, "is_business_travel_ready": false, "is_fully_refundable": false, "is_new_listing": false, "lat": 20.90011, "lng": -86.8546, "localized_city": "Canc\u00fan", "localized_neighborhood": null, "listing_name": "THE BEACH RESIDENCES, BEACH FRONT 3 BEDROOM CONDO", "person_capacity": 8, "picture_count": 44, "reviews_count": 4, "room_type_category": "entire_home", "star_rating": 5.0, "avg_rating": 5.0, "can_instant_book": true, "monthly_price_factor": 0.75, "weekly_price_factor": 0.85, "currency": "CAD", "amt_w_service": 327.0, "rate_type": "nightly", "num_beds": 4, "host_reviews": 49, "accuracy": 10, "checkin": 10, "cleanliness": 10, "communication": 10, "value": 10, "location": 10, "guest_satisfication": 100, "response_rate": 100, "response_time": "within an hour"},
{"is_superhost": false, "host_id": "38229871", "price": 329.0, "url": "https://www.airbnb.com/rooms/29382045", "bathrooms": 2.0, "bedrooms": 2, "is_business_travel_ready": false, "is_fully_refundable": false, "is_new_listing": false, "lat": 20.854675, "lng": -86.872429, "localized_city": "Puerto Morelos", "localized_neighborhood": null, "listing_name": "Casita Manglar, 2BR Beachfront in Puerto Morelos", "person_capacity": 4, "picture_count": 35, "reviews_count": 0, "room_type_category": "entire_home", "star_rating": null, "avg_rating": 0.0, "can_instant_book": true, "monthly_price_factor": 0.95, "weekly_price_factor": 1.0, "currency": "CAD", "amt_w_service": 329.0, "rate_type": "nightly", "num_beds": 2, "host_reviews": 8, "accuracy": 0, "checkin": 0, "cleanliness": 0, "communication": 0, "value": 0, "location": 0, "guest_satisfication": 0, "response_rate": 0, "response_time": ""},
{"is_superhost": false, "host_id": "143158916", "price": 329.0, "url": "https://www.airbnb.com/rooms/35299577", "bathrooms": 2.0, "bedrooms": 2, "is_business_travel_ready": false, "is_fully_refundable": false, "is_new_listing": true, "lat": 21.25899, "lng": -86.74568, "localized_city": "Isla Mujeres", "localized_neighborhood": null, "listing_name": "Casa Mia", "person_capacity": 4, "picture_count": 23, "reviews_count": 0, "room_type_category": "entire_home", "star_rating": null, "avg_rating": 0.0, "can_instant_book": false, "monthly_price_factor": 1.0, "weekly_price_factor": 1.0, "currency": "CAD", "amt_w_service": 329.0, "rate_type": "nightly", "num_beds": 2, "host_reviews": 179, "accuracy": 0, "checkin": 0, "cleanliness": 0, "communication": 0, "value": 0, "location": 0, "guest_satisfication": 0, "response_rate": 100, "response_time": "within an hour"},
{"is_superhost": false, "host_id": "121896255", "price": 322.0, "url": "https://www.airbnb.com/rooms/32836044", "bathrooms": 2.0, "bedrooms": 3, "is_business_travel_ready": false, "is_fully_refundable": false, "is_new_listing": false, "lat": 20.87302, "lng": -86.86671, "localized_city": "Puerto Morelos", "localized_neighborhood": null, "listing_name": "Riviera Luxury beach Residences", "person_capacity": 8, "picture_count": 32, "reviews_count": 0, "room_type_category": "entire_home", "star_rating": null, "avg_rating": 0.0, "can_instant_book": true, "monthly_price_factor": 0.85, "weekly_price_factor": 0.95, "currency": "CAD", "amt_w_service": 322.0, "rate_type": "nightly", "num_beds": 5, "host_reviews": 42, "accuracy": 0, "checkin": 0, "cleanliness": 0, "communication": 0, "value": 0, "location": 0, "guest_satisfication": 0, "response_rate": 100, "response_time": "within an hour"},
{"is_superhost": false, "host_id": "105076046", "price": 329.0, "url": "https://www.airbnb.com/rooms/16393537", "bathrooms": 4.5, "bedrooms": 4, "is_business_travel_ready": false, "is_fully_refundable": false, "is_new_listing": false, "lat": 20.89302, "lng": -86.85939, "localized_city": "Canc\u00fan", "localized_neighborhood": null, "listing_name": "PEACEFUL HOUSE FRONT OF THE MEXICAN CARIBBEAN", "person_capacity": 10, "picture_count": 56, "reviews_count": 8, "room_type_category": "entire_home", "star_rating": 4.5, "avg_rating": 4.43, "can_instant_book": false, "monthly_price_factor": 1.0, "weekly_price_factor": 1.0, "currency": "CAD", "amt_w_service": 329.0, "rate_type": "nightly", "num_beds": 7, "host_reviews": 11, "accuracy": 9, "checkin": 10, "cleanliness": 9, "communication": 10, "value": 9, "location": 9, "guest_satisfication": 89, "response_rate": 100, "response_time": "within a few hours"},
{"is_superhost": false, "host_id": "202823853", "price": 329.0, "url": "https://www.airbnb.com/rooms/26984692", "bathrooms": 2.0, "bedrooms": 1, "is_business_travel_ready": false, "is_fully_refundable": false, "is_new_listing": false, "lat": 21.23099, "lng": -86.80302, "localized_city": "Canc\u00fan", "localized_neighborhood": null, "listing_name": "Villa Del Palmar", "person_capacity": 4, "picture_count": 27, "reviews_count": 1, "room_type_category": "private_room", "star_rating": null, "avg_rating": 0.0, "can_instant_book": false, "monthly_price_factor": 1.0, "weekly_price_factor": 1.0, "currency": "CAD", "amt_w_service": 329.0, "rate_type": "nightly", "num_beds": 2, "host_reviews": 1, "accuracy": 0, "checkin": 0, "cleanliness": 0, "communication": 0, "value": 0, "location": 0, "guest_satisfication": 0, "response_rate": 0, "response_time": ""},
{"is_superhost": false, "host_id": "210695950", "price": 329.0, "url": "https://www.airbnb.com/rooms/27891682", "bathrooms": 2.0, "bedrooms": 2, "is_business_travel_ready": false, "is_fully_refundable": false, "is_new_listing": false, "lat": 21.12864, "lng": -86.81804, "localized_city": "Canc\u00fan", "localized_neighborhood": null, "listing_name": "Casa cancun", "person_capacity": 4, "picture_count": 1, "reviews_count": 0, "room_type_category": "private_room", "star_rating": null, "avg_rating": 0.0, "can_instant_book": true, "monthly_price_factor": 1.0, "weekly_price_factor": 1.0, "currency": "CAD", "amt_w_service": 329.0, "rate_type": "nightly", "num_beds": 2, "host_reviews": 0, "accuracy": 0, "checkin": 0, "cleanliness": 0, "communication": 0, "value": 0, "location": 0, "guest_satisfication": 0, "response_rate": 0, "response_time": ""},
{"is_superhost": false, "host_id": "154820839", "price": 329.0, "url": "https://www.airbnb.com/rooms/21377399", "bathrooms": 2.0, "bedrooms": 2, "is_business_travel_ready": false, "is_fully_refundable": false, "is_new_listing": false, "lat": 20.83789, "lng": -86.91067, "localized_city": "Quintana Roo", "localized_neighborhood": null, "listing_name": "EXPERIMENTA VIVIR EN UNA CABANA EN LA JUNGLA", "person_capacity": 8, "picture_count": 12, "reviews_count": 0, "room_type_category": "entire_home", "star_rating": null, "avg_rating": 0.0, "can_instant_book": true, "monthly_price_factor": 0.85, "weekly_price_factor": 0.9, "currency": "CAD", "amt_w_service": 329.0, "rate_type": "nightly", "num_beds": 6, "host_reviews": 0, "accuracy": 0, "checkin": 0, "cleanliness": 0, "communication": 0, "value": 0, "location": 0, "guest_satisfication": 0, "response_rate": 0, "response_time": ""},
{"is_superhost": false, "host_id": "19435703", "price": 329.0, "url": "https://www.airbnb.com/rooms/3786885", "bathrooms": 2.0, "bedrooms": 2, "is_business_travel_ready": false, "is_fully_refundable": false, "is_new_listing": false, "lat": 21.31656, "lng": -86.80867, "localized_city": "Isla Blanca", "localized_neighborhood": null, "listing_name": "Isla Blanca Beachfront Home Near Cancun", "person_capacity": 6, "picture_count": 9, "reviews_count": 5, "room_type_category": "entire_home", "star_rating": 5.0, "avg_rating": 5.0, "can_instant_book": false, "monthly_price_factor": 1.0, "weekly_price_factor": 1.0, "currency": "CAD", "amt_w_service": 329.0, "rate_type": "nightly", "num_beds": 3, "host_reviews": 19, "accuracy": 10, "checkin": 10, "cleanliness": 10, "communication": 10, "value": 10, "location": 10, "guest_satisfication": 100, "response_rate": 100, "response_time": "within a few hours"},
{"is_superhost": false, "host_id": "179927880", "price": 329.0, "url": "https://www.airbnb.com/rooms/23933910", "bathrooms": 2.0, "bedrooms": 2, "is_business_travel_ready": false, "is_fully_refundable": false, "is_new_listing": false, "lat": 21.17979, "lng": -86.80952, "localized_city": "Canc\u00fan", "localized_neighborhood": null, "listing_name": "Amara Beach Condos", "person_capacity": 4, "picture_count": 17, "reviews_count": 1, "room_type_category": "private_room", "star_rating": null, "avg_rating": 0.0, "can_instant_book": false, "monthly_price_factor": 0.7, "weekly_price_factor": 0.8, "currency": "CAD", "amt_w_service": 329.0, "rate_type": "nightly", "num_beds": 3, "host_reviews": 3, "accuracy": 0, "checkin": 0, "cleanliness": 0, "communication": 0, "value": 0, "location": 0, "guest_satisfication": 0, "response_rate": 0, "response_time": ""},
{"is_superhost": false, "host_id": "5132938", "price": 329.0, "url": "https://www.airbnb.com/rooms/1150715", "bathrooms": 2.0, "bedrooms": 2, "is_business_travel_ready": false, "is_fully_refundable": false, "is_new_listing": false, "lat": 20.83972, "lng": -86.88167, "localized_city": "Puerto Morelos", "localized_neighborhood": null, "listing_name": "On the Beach in Puerto Morelos", "person_capacity": 6, "picture_count": 14, "reviews_count": 0, "room_type_category": "entire_home", "star_rating": null, "avg_rating": 0.0, "can_instant_book": false, "monthly_price_factor": 1.0, "weekly_price_factor": 0.93, "currency": "CAD", "amt_w_service": 329.0, "rate_type": "nightly", "num_beds": 4, "host_reviews": 1, "accuracy": 10, "checkin": 6, "cleanliness": 8, "communication": 10, "value": 10, "location": 6, "guest_satisfication": 100, "response_rate": 100, "response_time": "within a day"},
{"is_superhost": false, "host_id": "171034788", "price": 329.0, "url": "https://www.airbnb.com/rooms/27259002", "bathrooms": 1.0, "bedrooms": 1, "is_business_travel_ready": false, "is_fully_refundable": false, "is_new_listing": false, "lat": 21.11912, "lng": -86.76749, "localized_city": "Canc\u00fan", "localized_neighborhood": null, "listing_name": "Cancun Beachfront and Large Pool Condo", "person_capacity": 2, "picture_count": 5, "reviews_count": 0, "room_type_category": "private_room", "star_rating": null, "avg_rating": 0.0, "can_instant_book": false, "monthly_price_factor": 1.0, "weekly_price_factor": 1.0, "currency": "CAD", "amt_w_service": 329.0, "rate_type": "nightly", "num_beds": 2, "host_reviews": 0, "accuracy": 0, "checkin": 0, "cleanliness": 0, "communication": 0, "value": 0, "location": 0, "guest_satisfication": 0, "response_rate": 0, "response_time": ""},
{"is_superhost": false, "host_id": "24230409", "price": 327.0, "url": "https://www.airbnb.com/rooms/4943573", "bathrooms": 1.0, "bedrooms": 1, "is_business_travel_ready": false, "is_fully_refundable": false, "is_new_listing": false, "lat": 21.23305, "lng": -86.80327, "localized_city": "Canc\u00fan", "localized_neighborhood": null, "listing_name": "Luxurious one bedroom on the beach", "person_capacity": 4, "picture_count": 11, "reviews_count": 2, "room_type_category": "entire_home", "star_rating": null, "avg_rating": 4.5, "can_instant_book": false, "monthly_price_factor": 1.0, "weekly_price_factor": 1.0, "currency": "CAD", "amt_w_service": 327.0, "rate_type": "nightly", "num_beds": 2, "host_reviews": 9, "accuracy": 10, "checkin": 10, "cleanliness": 10, "communication": 10, "value": 10, "location": 9, "guest_satisfication": 90, "response_rate": 0, "response_time": ""},
{"is_superhost": false, "host_id": "19435703", "price": 329.0, "url": "https://www.airbnb.com/rooms/4808432", "bathrooms": 2.0, "bedrooms": 2, "is_business_travel_ready": false, "is_fully_refundable": false, "is_new_listing": false, "lat": 21.2828, "lng": -86.81632, "localized_city": "Canc\u00fan", "localized_neighborhood": null, "listing_name": "Beachfront home near Cancun", "person_capacity": 6, "picture_count": 7, "reviews_count": 0, "room_type_category": "entire_home", "star_rating": null, "avg_rating": 0.0, "can_instant_book": false, "monthly_price_factor": 1.0, "weekly_price_factor": 1.0, "currency": "CAD", "amt_w_service": 329.0, "rate_type": "nightly", "num_beds": 3, "host_reviews": 19, "accuracy": 0, "checkin": 0, "cleanliness": 0, "communication": 0, "value": 0, "location": 0, "guest_satisfication": 0, "response_rate": 100, "response_time": "within a few hours"},
{"is_superhost": false, "host_id": "235959", "price": 327.0, "url": "https://www.airbnb.com/rooms/18529337", "bathrooms": 1.0, "bedrooms": 1, "is_business_travel_ready": false, "is_fully_refundable": false, "is_new_listing": false, "lat": 20.84295, "lng": -86.87918, "localized_city": "Puerto Morelos", "localized_neighborhood": null, "listing_name": "SAIL BOAT BLOCK ISLAND 40- MARINA ELCID", "person_capacity": 2, "picture_count": 1, "reviews_count": 0, "room_type_category": "entire_home", "star_rating": null, "avg_rating": 0.0, "can_instant_book": false, "monthly_price_factor": 0.65, "weekly_price_factor": 0.75, "currency": "CAD", "amt_w_service": 327.0, "rate_type": "nightly", "num_beds": 2, "host_reviews": 8, "accuracy": 0, "checkin": 0, "cleanliness": 0, "communication": 0, "value": 0, "location": 0, "guest_satisfication": 0, "response_rate": 0, "response_time": ""},
{"is_superhost": false, "host_id": "37842019", "price": 329.0, "url": "https://www.airbnb.com/rooms/7227720", "bathrooms": 3.0, "bedrooms": 1, "is_business_travel_ready": false, "is_fully_refundable": false, "is_new_listing": false, "lat": 21.10433, "lng": -86.76271, "localized_city": "Canc\u00fan", "localized_neighborhood": null, "listing_name": "Oceanfront Condo in Cancun", "person_capacity": 8, "picture_count": 16, "reviews_count": 1, "room_type_category": "private_room", "star_rating": null, "avg_rating": 5.0, "can_instant_book": false, "monthly_price_factor": 1.0, "weekly_price_factor": 1.0, "currency": "CAD", "amt_w_service": 329.0, "rate_type": "nightly", "num_beds": 5, "host_reviews": 5, "accuracy": 10, "checkin": 10, "cleanliness": 10, "communication": 10, "value": 10, "location": 10, "guest_satisfication": 100, "response_rate": 0, "response_time": ""},
{"is_superhost": false, "host_id": "85672777", "price": 329.0, "url": "https://www.airbnb.com/rooms/14163505", "bathrooms": 1.0, "bedrooms": 1, "is_business_travel_ready": false, "is_fully_refundable": false, "is_new_listing": false, "lat": 21.11825, "lng": -86.75667, "localized_city": "Canc\u00fan", "localized_neighborhood": null, "listing_name": "Stunning beach front resort in the heart of Cancun", "person_capacity": 4, "picture_count": 5, "reviews_count": 1, "room_type_category": "entire_home", "star_rating": null, "avg_rating": 0.0, "can_instant_book": false, "monthly_price_factor": 1.0, "weekly_price_factor": 1.0, "currency": "CAD", "amt_w_service": 329.0, "rate_type": "nightly", "num_beds": 2, "host_reviews": 1, "accuracy": 0, "checkin": 0, "cleanliness": 0, "communication": 0, "value": 0, "location": 0, "guest_satisfication": 0, "response_rate": 0, "response_time": ""},
{"is_superhost": false, "host_id": "26308986", "price": 329.0, "url": "https://www.airbnb.com/rooms/9116719", "bathrooms": 2.0, "bedrooms": 2, "is_business_travel_ready": false, "is_fully_refundable": false, "is_new_listing": false, "lat": 21.23693, "lng": -86.73718, "localized_city": "Isla Mujeres", "localized_neighborhood": null, "listing_name": "Villa Keh", "person_capacity": 4, "picture_count": 24, "reviews_count": 20, "room_type_category": "entire_home", "star_rating": 5.0, "avg_rating": 4.84, "can_instant_book": true, "monthly_price_factor": 1.0, "weekly_price_factor": 1.0, "currency": "CAD", "amt_w_service": 329.0, "rate_type": "nightly", "num_beds": 2, "host_reviews": 186, "accuracy": 9, "checkin": 10, "cleanliness": 10, "communication": 9, "value": 10, "location": 9, "guest_satisfication": 97, "response_rate": 100, "response_time": "within an hour"},
{"is_superhost": false, "host_id": "114199067", "price": 330.0, "url": "https://www.airbnb.com/rooms/32641200", "bathrooms": 3.0, "bedrooms": 3, "is_business_travel_ready": false, "is_fully_refundable": false, "is_new_listing": false, "lat": 21.20801, "lng": -86.71544, "localized_city": "Isla Mujeres", "localized_neighborhood": null, "listing_name": "Sea view home w/ private pool, garden, terraces & beautiful views!", "person_capacity": 12, "picture_count": 30, "reviews_count": 0, "room_type_category": "entire_home", "star_rating": null, "avg_rating": 0.0, "can_instant_book": true, "monthly_price_factor": 1.0, "weekly_price_factor": 1.0, "currency": "CAD", "amt_w_service": 330.0, "rate_type": "nightly", "num_beds": 5, "host_reviews": 168, "accuracy": 0, "checkin": 0, "cleanliness": 0, "communication": 0, "value": 0, "location": 0, "guest_satisfication": 0, "response_rate": 100, "response_time": "within an hour"},
{"is_superhost": false, "host_id": "143158916", "price": 327.0, "url": "https://www.airbnb.com/rooms/21052396", "bathrooms": 2.0, "bedrooms": 2, "is_business_travel_ready": false, "is_fully_refundable": false, "is_new_listing": false, "lat": 21.231506, "lng": -86.728287, "localized_city": "Isla Mujeres", "localized_neighborhood": null, "listing_name": "Villa Bienvenido at Isla 33", "person_capacity": 5, "picture_count": 15, "reviews_count": 8, "room_type_category": "entire_home", "star_rating": 5.0, "avg_rating": 4.86, "can_instant_book": true, "monthly_price_factor": 0.8, "weekly_price_factor": 1.0, "currency": "CAD", "amt_w_service": 327.0, "rate_type": "nightly", "num_beds": 2, "host_reviews": 179, "accuracy": 10, "checkin": 10, "cleanliness": 10, "communication": 9, "value": 10, "location": 9, "guest_satisfication": 97, "response_rate": 100, "response_time": "within an hour"},
{"is_superhost": false, "host_id": "77225843", "price": 329.0, "url": "https://www.airbnb.com/rooms/33587969", "bathrooms": 1.0, "bedrooms": 1, "is_business_travel_ready": false, "is_fully_refundable": false, "is_new_listing": false, "lat": 21.05811, "lng": -86.78085, "localized_city": "Canc\u00fan", "localized_neighborhood": null, "listing_name": "Luxury Beach Club Suite (Adults Only)", "person_capacity": 2, "picture_count": 19, "reviews_count": 0, "room_type_category": "entire_home", "star_rating": null, "avg_rating": 0.0, "can_instant_book": false, "monthly_price_factor": 1.0, "weekly_price_factor": 1.0, "currency": "CAD", "amt_w_service": 329.0, "rate_type": "nightly", "num_beds": 1, "host_reviews": 1, "accuracy": 0, "checkin": 0, "cleanliness": 0, "communication": 0, "value": 0, "location": 0, "guest_satisfication": 0, "response_rate": 67, "response_time": "within a day"},
{"is_superhost": false, "host_id": "26266660", "price": 322.0, "url": "https://www.airbnb.com/rooms/5085313", "bathrooms": 2.0, "bedrooms": 2, "is_business_travel_ready": false, "is_fully_refundable": false, "is_new_listing": false, "lat": 21.1031, "lng": -86.76262, "localized_city": "Canc\u00fan", "localized_neighborhood": null, "listing_name": "Villa Con Vista al Mar 2 habitaciones #08", "person_capacity": 5, "picture_count": 24, "reviews_count": 1, "room_type_category": "entire_home", "star_rating": null, "avg_rating": 5.0, "can_instant_book": true, "monthly_price_factor": 1.0, "weekly_price_factor": 1.0, "currency": "CAD", "amt_w_service": 322.0, "rate_type": "nightly", "num_beds": 3, "host_reviews": 95, "accuracy": 10, "checkin": 10, "cleanliness": 8, "communication": 10, "value": 10, "location": 8, "guest_satisfication": 100, "response_rate": 100, "response_time": "within an hour"},
{"is_superhost": false, "host_id": "34268526", "price": 329.0, "url": "https://www.airbnb.com/rooms/6552018", "bathrooms": 2.5, "bedrooms": 2, "is_business_travel_ready": false, "is_fully_refundable": false, "is_new_listing": false, "lat": 21.24057, "lng": -86.80365, "localized_city": "Canc\u00fan", "localized_neighborhood": null, "listing_name": "NEW  Luxury  Condo at New Cancun", "person_capacity": 5, "picture_count": 38, "reviews_count": 8, "room_type_category": "entire_home", "star_rating": 4.5, "avg_rating": 4.43, "can_instant_book": true, "monthly_price_factor": 0.41, "weekly_price_factor": 1.0, "currency": "CAD", "amt_w_service": 329.0, "rate_type": "nightly", "num_beds": 3, "host_reviews": 10, "accuracy": 9, "checkin": 9, "cleanliness": 8, "communication": 10, "value": 9, "location": 10, "guest_satisfication": 89, "response_rate": 100, "response_time": "within an hour"},
{"is_superhost": true, "host_id": "34694262", "price": 329.0, "url": "https://www.airbnb.com/rooms/28458893", "bathrooms": 3.5, "bedrooms": 3, "is_business_travel_ready": false, "is_fully_refundable": false, "is_new_listing": false, "lat": 21.23563, "lng": -86.73102, "localized_city": "Isla Mujeres", "localized_neighborhood": null, "listing_name": "MAYAKAAN HOUSES, FANTASTIC VIEW BEACH w/ROOFTOP 2", "person_capacity": 8, "picture_count": 46, "reviews_count": 11, "room_type_category": "entire_home", "star_rating": 5.0, "avg_rating": 5.0, "can_instant_book": true, "monthly_price_factor": 0.8, "weekly_price_factor": 0.9, "currency": "CAD", "amt_w_service": 329.0, "rate_type": "nightly", "num_beds": 5, "host_reviews": 67, "accuracy": 10, "checkin": 10, "cleanliness": 10, "communication": 10, "value": 10, "location": 10, "guest_satisfication": 100, "response_rate": 100, "response_time": "within an hour"},
{"is_superhost": false, "host_id": "61875323", "price": 329.0, "url": "https://www.airbnb.com/rooms/26993581", "bathrooms": 3.0, "bedrooms": 4, "is_business_travel_ready": false, "is_fully_refundable": false, "is_new_listing": false, "lat": 21.10296, "lng": -86.76288, "localized_city": "Cancun", "localized_neighborhood": null, "listing_name": "Sleep by the Blue Paradise", "person_capacity": 8, "picture_count": 16, "reviews_count": 4, "room_type_category": "entire_home", "star_rating": 4.5, "avg_rating": 4.67, "can_instant_book": false, "monthly_price_factor": 0.8, "weekly_price_factor": 0.9, "currency": "CAD", "amt_w_service": 329.0, "rate_type": "nightly", "num_beds": 5, "host_reviews": 4, "accuracy": 10, "checkin": 10, "cleanliness": 10, "communication": 10, "value": 9, "location": 10, "guest_satisfication": 93, "response_rate": 100, "response_time": "within a few hours"},
{"is_superhost": false, "host_id": "59044646", "price": 329.0, "url": "https://www.airbnb.com/rooms/33679946", "bathrooms": 1.0, "bedrooms": 0, "is_business_travel_ready": false, "is_fully_refundable": false, "is_new_listing": false, "lat": 21.23143, "lng": -86.80289, "localized_city": "Canc\u00fan", "localized_neighborhood": null, "listing_name": "Spend Your New Year in Cancun", "person_capacity": 4, "picture_count": 29, "reviews_count": 0, "room_type_category": "private_room", "star_rating": null, "avg_rating": 0.0, "can_instant_book": true, "monthly_price_factor": 1.0, "weekly_price_factor": 1.0, "currency": "CAD", "amt_w_service": 329.0, "rate_type": "nightly", "num_beds": 2, "host_reviews": 0, "accuracy": 0, "checkin": 0, "cleanliness": 0, "communication": 0, "value": 0, "location": 0, "guest_satisfication": 0, "response_rate": 0, "response_time": ""},
{"is_superhost": false, "host_id": "56913550", "price": 329.0, "url": "https://www.airbnb.com/rooms/22956866", "bathrooms": 3.5, "bedrooms": 4, "is_business_travel_ready": false, "is_fully_refundable": false, "is_new_listing": false, "lat": 21.14305, "lng": -86.78995, "localized_city": "Canc\u00fan", "localized_neighborhood": null, "listing_name": "Wonderful Lagoon House in Hotel Zone", "person_capacity": 10, "picture_count": 17, "reviews_count": 1, "room_type_category": "entire_home", "star_rating": null, "avg_rating": 5.0, "can_instant_book": false, "monthly_price_factor": 0.7, "weekly_price_factor": 0.88, "currency": "CAD", "amt_w_service": 329.0, "rate_type": "nightly", "num_beds": 7, "host_reviews": 61, "accuracy": 10, "checkin": 10, "cleanliness": 10, "communication": 10, "value": 10, "location": 10, "guest_satisfication": 100, "response_rate": 100, "response_time": "within a few hours"},
{"is_superhost": false, "host_id": "59044646", "price": 329.0, "url": "https://www.airbnb.com/rooms/33471489", "bathrooms": 1.0, "bedrooms": 0, "is_business_travel_ready": false, "is_fully_refundable": false, "is_new_listing": false, "lat": 21.231916, "lng": -86.803886, "localized_city": "Canc\u00fan", "localized_neighborhood": null, "listing_name": "Holiday Escape at the Villa Del Palmar Resort", "person_capacity": 4, "picture_count": 29, "reviews_count": 0, "room_type_category": "private_room", "star_rating": null, "avg_rating": 0.0, "can_instant_book": true, "monthly_price_factor": 1.0, "weekly_price_factor": 1.0, "currency": "CAD", "amt_w_service": 329.0, "rate_type": "nightly", "num_beds": 2, "host_reviews": 0, "accuracy": 0, "checkin": 0, "cleanliness": 0, "communication": 0, "value": 0, "location": 0, "guest_satisfication": 0, "response_rate": 0, "response_time": ""},
{"is_superhost": false, "host_id": "96086504", "price": 320.0, "url": "https://www.airbnb.com/rooms/31065685", "bathrooms": 3.5, "bedrooms": 3, "is_business_travel_ready": false, "is_fully_refundable": false, "is_new_listing": false, "lat": 21.03132, "lng": -86.80419, "localized_city": "Canc\u00fan ", "localized_neighborhood": null, "listing_name": "Departamento de lujo beach front", "person_capacity": 8, "picture_count": 22, "reviews_count": 3, "room_type_category": "entire_home", "star_rating": 5.0, "avg_rating": 5.0, "can_instant_book": true, "monthly_price_factor": 0.9, "weekly_price_factor": 0.95, "currency": "CAD", "amt_w_service": 320.0, "rate_type": "nightly", "num_beds": 5, "host_reviews": 232, "accuracy": 10, "checkin": 10, "cleanliness": 9, "communication": 10, "value": 10, "location": 8, "guest_satisfication": 100, "response_rate": 100, "response_time": "within an hour"},
{"is_superhost": false, "host_id": "29894782", "price": 329.0, "url": "https://www.airbnb.com/rooms/30739781", "bathrooms": 1.0, "bedrooms": 3, "is_business_travel_ready": false, "is_fully_refundable": false, "is_new_listing": false, "lat": 21.09906, "lng": -86.76436, "localized_city": "Canc\u00fan", "localized_neighborhood": null, "listing_name": "Beachfront 3 room suite inside of an art museum!", "person_capacity": 6, "picture_count": 14, "reviews_count": 2, "room_type_category": "entire_home", "star_rating": null, "avg_rating": 5.0, "can_instant_book": true, "monthly_price_factor": 1.0, "weekly_price_factor": 1.0, "currency": "CAD", "amt_w_service": 329.0, "rate_type": "nightly", "num_beds": 3, "host_reviews": 54, "accuracy": 10, "checkin": 10, "cleanliness": 10, "communication": 10, "value": 10, "location": 10, "guest_satisfication": 100, "response_rate": 100, "response_time": "within an hour"},
{"is_superhost": false, "host_id": "4223659", "price": 329.0, "url": "https://www.airbnb.com/rooms/802457", "bathrooms": 3.5, "bedrooms": 3, "is_business_travel_ready": false, "is_fully_refundable": false, "is_new_listing": false, "lat": 21.14485, "lng": -86.78945, "localized_city": "Canc\u00fan", "localized_neighborhood": null, "listing_name": "Casa frente a la laguna con muelle 10", "person_capacity": 6, "picture_count": 92, "reviews_count": 14, "room_type_category": "entire_home", "star_rating": 5.0, "avg_rating": 4.86, "can_instant_book": false, "monthly_price_factor": 1.0, "weekly_price_factor": 1.0, "currency": "CAD", "amt_w_service": 329.0, "rate_type": "nightly", "num_beds": 4, "host_reviews": 36, "accuracy": 10, "checkin": 10, "cleanliness": 9, "communication": 10, "value": 9, "location": 10, "guest_satisfication": 97, "response_rate": 0, "response_time": ""}
]